Metadata-Version: 2.1
Name: odoo-addon-exportar_deposito_xls
Version: 17.0.1.1.2.3
Requires-Python: >=3.10
Requires-Dist: odoo-addon-exportar_stock_editorial_xls>=17.0dev,<17.1dev
Requires-Dist: odoo-addon-gestion_editorial>=17.0dev,<17.1dev
Requires-Dist: odoo>=17.0a,<17.1dev
Summary: =?utf-8?q?Muestra_el_stock_actual_por_dep=C3=B3sito=2E?=
Home-page: https://framagit.org/devcontrol
License: AGPL-3
Author: Colectivo DEVCONTROL
Classifier: Programming Language :: Python
Classifier: Framework :: Odoo
Classifier: Framework :: Odoo :: 17.0
Classifier: License :: OSI Approved :: GNU Affero General Public License v3
